README.md
setup.py
cm_client/__init__.py
cm_client/api_client.py
cm_client/configuration.py
cm_client/rest.py
cm_client.egg-info/PKG-INFO
cm_client.egg-info/SOURCES.txt
cm_client.egg-info/dependency_links.txt
cm_client.egg-info/requires.txt
cm_client.egg-info/top_level.txt
cm_client/apis/__init__.py
cm_client/apis/activities_resource_api.py
cm_client/apis/all_hosts_resource_api.py
cm_client/apis/audits_resource_api.py
cm_client/apis/auth_role_metadatas_resource_api.py
cm_client/apis/auth_roles_resource_api.py
cm_client/apis/auth_service_resource_api.py
cm_client/apis/auth_service_role_commands_resource_api.py
cm_client/apis/auth_service_role_config_groups_resource_api.py
cm_client/apis/auth_service_roles_resource_api.py
cm_client/apis/batch_resource_api.py
cm_client/apis/cdp_resource_api.py
cm_client/apis/cert_manager_resource_api.py
cm_client/apis/cloudera_manager_resource_api.py
cm_client/apis/clusters_resource_api.py
cm_client/apis/cm_peers_resource_api.py
cm_client/apis/commands_resource_api.py
cm_client/apis/control_planes_resource_api.py
cm_client/apis/csp_resource_api.py
cm_client/apis/dashboards_resource_api.py
cm_client/apis/data_contexts_resource_api.py
cm_client/apis/events_resource_api.py
cm_client/apis/external_accounts_resource_api.py
cm_client/apis/external_user_mappings_resource_api.py
cm_client/apis/host_templates_resource_api.py
cm_client/apis/hosts_resource_api.py
cm_client/apis/impala_queries_resource_api.py
cm_client/apis/mgmt_role_commands_resource_api.py
cm_client/apis/mgmt_role_config_groups_resource_api.py
cm_client/apis/mgmt_roles_resource_api.py
cm_client/apis/mgmt_service_resource_api.py
cm_client/apis/nameservices_resource_api.py
cm_client/apis/parcel_resource_api.py
cm_client/apis/parcels_resource_api.py
cm_client/apis/process_resource_api.py
cm_client/apis/replications_resource_api.py
cm_client/apis/role_commands_resource_api.py
cm_client/apis/role_config_groups_resource_api.py
cm_client/apis/roles_resource_api.py
cm_client/apis/services_resource_api.py
cm_client/apis/snapshots_resource_api.py
cm_client/apis/tags_resource_api.py
cm_client/apis/time_series_resource_api.py
