Metadata-Version: 1.0
Name: cm-client
Version: 45.0.4
Summary: Cloudera Manager API
Home-page: UNKNOWN
Author: UNKNOWN
Author-email: UNKNOWN
License: UNKNOWN
Keywords: Swagger,Cloudera Manager API
Platform: UNKNOWN
